jogo_damas/__init__.py
jogo_damas/main.py
jogo_damas/classes/__init__.py
jogo_damas/classes/controlador.py
jogo_damas/classes/peca.py
jogo_damas/classes/tabuleiro.py
jogo_damas/ui/__init__.py
jogo_damas/ui/botao.py
jogo_damas/ui/telas.py
jogo_damas/utils/__init__.py
jogo_damas/utils/complementos.py
jogo_damas/utils/config.py
jogo_damas/utils/interface.py
jogo_damas_brasileiras-0.1.0.dist-info/METADATA
jogo_damas_brasileiras-0.1.0.dist-info/WHEEL
jogo_damas_brasileiras-0.1.0.dist-info/entry_points.txt
jogo_damas_brasileiras-0.1.0.dist-info/top_level.txt
jogo_damas_brasileiras-0.1.0.dist-info/RECORD
