Metadata-Version: 2.4
Name: jogo-damas-brasileiras
Version: 0.1.0
Summary: Um jogo de damas em Python com pygame.
Author-email: Stefany Nicole Santos Alves <stefany.nicole.santos.alves@ccc.ufcg.edu.br>, Rebeca de Medeiros Silva <rebeca.de.medeiros.silva@ccc.ufcg.edu.br>
Project-URL: GitHub, https://github.com/rebecamdrs/Projeto-Damas
Project-URL: Vídeo, https://youtu.be/y_fSPHQ6510?si=7CYMslPc9dpVqPJP
Requires-Python: >=3.8
Requires-Dist: pygame
